packworker/__init__.py
packworker/bin.py
packworker/compute_loading.py
packworker/constant.py
packworker/item.py
packworker/worker.py
packworker-0.1.3.dist-info/LICENSE
packworker-0.1.3.dist-info/METADATA
packworker-0.1.3.dist-info/WHEEL
packworker-0.1.3.dist-info/RECORD
