Metadata-Version: 2.1
Name: packworker
Version: 0.1.3
Summary: 
License: MIT
Author: Nguyen Anh Tuan
Author-email: nanhtuan3896@gmail.com
Requires-Python: >=3.9,<4.0
Classifier: License :: OSI Approved :: MIT License
Classifier: Programming Language :: Python :: 3
Classifier: Programming Language :: Python :: 3.9
Classifier: Programming Language :: Python :: 3.10
Classifier: Programming Language :: Python :: 3.11
Requires-Dist: click (>=8.1.7,<9.0.0)
Requires-Dist: rich (>=13.6.0,<14.0.0)
